cast/__init__.py
cast/admin.py
cast/admin_urls/audio.py
cast/admin_urls/transcript.py
cast/admin_urls/video.py
cast/api/__init__.py
cast/api/serializers.py
cast/api/urls.py
cast/api/viewmixins.py
cast/api/views.py
cast/apps.py
cast/appsettings.py
cast/blocks.py
cast/cast_and_wagtail_urls.py
cast/comments/__init__.py
cast/comments/apps.py
cast/comments/appsettings.py
cast/comments/forms.py
cast/comments/helper.py
cast/comments/migrations/0001_initial.py
cast/comments/migrations/__init__.py
cast/comments/models.py
cast/comments/receivers.py
cast/comments/templates/comments/base.html
cast/comments/templates/comments/comment.html
cast/comments/templates/comments/form.html
cast/comments/templates/comments/list.html
cast/comments/templates/comments/posted.html
cast/comments/templates/comments/preview.html
cast/comments/templates/fluent_comments/templatetags/ajax_comment_tags.html
cast/comments/templates/fluent_comments/templatetags/flat_list.html
cast/comments/templates/fluent_comments/templatetags/threaded_list.html
cast/comments/templatetags/__init__.py
cast/comments/templatetags/fluent_comments_tags.py
cast/comments/urls.py
cast/comments/utils.py
cast/comments/views.py
cast/context_processors.py
cast/devdata.py
cast/feeds.py
cast/filters.py
cast/forms.py
cast/locale/de/LC_MESSAGES/django.po
cast/management/commands/__init__.py
cast/management/commands/media_backup.py
cast/management/commands/media_replace.py
cast/management/commands/media_restore.py
cast/management/commands/media_sizes.py
cast/management/commands/media_stale.py
cast/management/commands/recalc_video_posters.py
cast/management/commands/storage_backend.py
cast/management/commands/sync_renditions.py
cast/migrations/0001_initial.py
cast/migrations/0002_remove_blog_description.py
cast/migrations/0003_remove_post_parent_blog.py
cast/migrations/0004_homepage_alias_for_page.py
cast/migrations/0005_auto_20201024_0613.py
cast/migrations/0006_auto_20210628_1628.py
cast/migrations/0007_alter_post_body.py
django_cast-0.2.52.dist-info/WHEEL
django_cast-0.2.52.dist-info/entry_points.txt
django_cast-0.2.52.dist-info/METADATA
django_cast-0.2.52.dist-info/RECORD
