Metadata-Version: 2.3
Name: django-cast
Version: 0.2.52
Summary: Django Cast is a blogging and podcasting package built on Django and Wagtail CMS
Keywords: blog,podcast,video,audio
Author: Jochen Wersdörfer, Dominik Geldmacher
Author-email: Jochen Wersdörfer <jochen-cast@wersdoerfer.de>, Dominik Geldmacher <oryon@cyberise.de>
Classifier: Environment :: Web Environment
Classifier: Framework :: Django
Classifier: Framework :: Django :: 4.2
Classifier: Framework :: Django :: 5.2
Classifier: Framework :: Django :: 6.0
Classifier: Intended Audience :: Developers
Classifier: License :: OSI Approved :: BSD License
Classifier: Topic :: Internet
Classifier: Development Status :: 3 - Alpha
Classifier: Environment :: Web Environment
Classifier: License :: OSI Approved :: MIT License
Classifier: Programming Language :: Python :: 3 :: Only
Classifier: Programming Language :: Python :: 3.11
Classifier: Programming Language :: Python :: 3.12
Classifier: Programming Language :: Python :: 3.13
Classifier: Programming Language :: Python :: 3.14
Classifier: Topic :: Internet :: WWW/HTTP
Classifier: Topic :: Internet :: WWW/HTTP :: Dynamic Content
Requires-Dist: crispy-bootstrap4
Requires-Dist: django
Requires-Dist: django-crispy-forms
Requires-Dist: django-contrib-comments
Requires-Dist: django-environ
Requires-Dist: django-filter
Requires-Dist: django-htmx
Requires-Dist: django-model-utils
Requires-Dist: django-threadedcomments
Requires-Dist: django-vite
Requires-Dist: pygments
Requires-Dist: python-slugify
Requires-Dist: rich
Requires-Dist: setuptools
Requires-Dist: wagtail
Requires-Python: >=3.11
Project-URL: Documentation, https://django-cast.readthedocs.io/en/latest/
Project-URL: Source, https://github.com/ephes/django-cast
